table_processor/__init__.py
table_processor/cli.py
table_processor/commands/convert_tables.py
table_processor/commands/merge_tables.py
table_processor/core/actions.py
table_processor/core/config.py
table_processor/core/constants.py
table_processor/core/convert.py
table_processor/core/functions/assign_id.py
table_processor/core/functions/flatten_row.py
table_processor/core/functions/get_nested_field_value.py
table_processor/core/functions/nest_row.py
table_processor/core/functions/search_column_value.py
table_processor/core/functions/set_flat_field_value.py
table_processor/core/functions/set_nested_field_value.py
table_processor/core/functions/set_row_value.py
table_processor/core/io/__init__.py
table_processor/core/io/io_csv.py
table_processor/core/io/io_excel.py
table_processor/core/io/io_json.py
table_processor/core/io/loader.py
table_processor/core/io/saver.py
table_processor/core/merge.py
table_processor/core/types.py
python_table_processor-0.3.12.dist-info/LICENSE
python_table_processor-0.3.12.dist-info/METADATA
python_table_processor-0.3.12.dist-info/WHEEL
python_table_processor-0.3.12.dist-info/entry_points.txt
python_table_processor-0.3.12.dist-info/RECORD
